{
  "users": [
    {
      "id": "7869",
      "username": "admin",
      "email": "admin@gmail.com",
      "password": "admin123",
      "admin": true
    },
    {
      "id": "1110",
      "username": "jane_smith",
      "email": "janesimth@yahoo.com",
      "password": "mypassword",
      "admin": true
    },
    {
      "id": "2766",
      "username": "Ayman",
      "email": "ayman@yahoo.com",
      "password": "mypassword",
      "admin": false
    },
    {
      "id": "560b",
      "email": "aya@yahoo.com",
      "password": "aya111111",
      "admin": false
    },
    {
      "id": "cb15",
      "username": "Ahmed",
      "email": "Ahmed@gmail.com",
      "password": "mypassword",
      "admin": false
    },
    {
      "id": "f772",
      "email": "rahma@gmail.com",
      "password": "rahma123",
      "admin": false
    },
    {
      "id": "64cd",
      "username": "Marwa",
      "email": "marwa@gmail.com",
      "password": "123456789",
      "admin": false
    },
    {
      "id": "22e8",
      "username": "Yasser",
      "email": "yasser@gmail.com",
      "password": "123412341234",
      "admin": false
    },
    {
      "id": "0060",
      "username": "Catrin",
      "email": "catrin@gmail.com",
      "password": "password1234",
      "admin": false
    }
  ]
}